README.md
setup.py
wadget/__init__.py
wadget/__main__.py
wadget/idgames.py
wadget/interface.py
wadget.egg-info/PKG-INFO
wadget.egg-info/SOURCES.txt
wadget.egg-info/dependency_links.txt
wadget.egg-info/entry_points.txt
wadget.egg-info/requires.txt
wadget.egg-info/top_level.txt