Metadata-Version: 2.1
Name: wadget
Version: 0.0.8
Summary: A multi-platform CLI /idgames client for downloading Doom addons quickly.
Home-page: UNKNOWN
Author: Avery Ross
License: MIT License
Platform: UNKNOWN
